Metadata-Version: 2.1
Name: automateWordPressPost
Version: 0.1.1
Summary: Automate WordPress Block Editor. Add post using docx file or html file.
Home-page: https://github.com/UmerMuxhal/automate-wordpress-post
Author: Umer Mughal
Author-email: umermuxhal@gmail.com
License: UNKNOWN
Download-URL: https://github.com/UmerMuxhal/automate-wordpress-post/archive/v_0.1.tar.gz
Keywords: automate,wordpres,post
Platform: UNKNOWN
Classifier: Programming Language :: Python :: 3
Classifier: License :: OSI Approved :: MIT License
Classifier: Intended Audience :: Developers
Requires-Python: >=3.6
